master_blaster/__init__.py
master_blaster/__main__.py
master_blaster-1.0.6.data/scripts/master-blaster
master_blaster-1.0.6.dist-info/LICENSE
master_blaster-1.0.6.dist-info/METADATA
master_blaster-1.0.6.dist-info/WHEEL
master_blaster-1.0.6.dist-info/top_level.txt
master_blaster-1.0.6.dist-info/RECORD
