Metadata-Version: 2.1
Name: master-blaster
Version: 1.0.6
Summary: Rename primary branches of code repositories.
Home-page: https://github.com/Twitchkidd/master-blaster
Author: Gareth Field
Author-email: field.gareth@gmail.com
License: UNKNOWN
Platform: UNKNOWN
Classifier: Programming Language :: Python :: 3
Classifier: License :: OSI Approved :: GNU General Public License v3 or later (GPLv3+)
Classifier: Operating System :: OS Independent
Requires-Python: >=3.6
